selia_templates/__init__.py
selia_templates/apps.py
selia_templates/settings.py
selia_templates/version.py
selia_templates/custom_tags/__init__.py
selia_templates/custom_tags/json_data.py
selia_templates/custom_tags/urls.py
selia_templates/custom_tags/utils.py
selia_templates/custom_tags/components/__init__.py
selia_templates/custom_tags/components/base.py
selia_templates/custom_tags/components/details.py
selia_templates/custom_tags/components/extra.py
selia_templates/custom_tags/components/filters.py
selia_templates/custom_tags/components/lists.py
selia_templates/custom_tags/components/navbars.py
selia_templates/locale/es/LC_MESSAGES/django.mo
selia_templates/locale/es/LC_MESSAGES/django.po
selia_templates/static/.DS_Store
selia_templates/static/selia_templates/.DS_Store
selia_templates/static/selia_templates/css/main.css
selia_templates/static/selia_templates/img/github-dark.png
selia_templates/static/selia_templates/img/github-light.png
selia_templates/static/selia_templates/img/selia.old.png
selia_templates/static/selia_templates/img/selia.png
selia_templates/static/selia_templates/js/base.js
selia_templates/static/selia_templates/vendor/bootstrap/css/bootstrap.min.css
selia_templates/static/selia_templates/vendor/bootstrap/css/bootstrap.min.css.map
selia_templates/static/selia_templates/vendor/bootstrap/js/bootstrap.bundle.min.js
selia_templates/static/selia_templates/vendor/bootstrap/js/bootstrap.bundle.min.js.map
selia_templates/static/selia_templates/vendor/fontawesome-free/css/all.min.css
selia_templates/static/selia_templates/vendor/fontawesome-free/css/fontawesome.min.css
selia_templates/static/selia_templates/vendor/fontawesome-free/js/all.min.js
selia_templates/static/selia_templates/vendor/fontawesome-free/js/fontawesome.min.js
selia_templates/static/selia_templates/vendor/fontawesome-free/webfonts/fa-brands-400.eot
selia_templates/static/selia_templates/vendor/fontawesome-free/webfonts/fa-brands-400.svg
selia_templates-0.1.2.dist-info/LICENCE
selia_templates-0.1.2.dist-info/METADATA
selia_templates-0.1.2.dist-info/WHEEL
selia_templates-0.1.2.dist-info/top_level.txt
selia_templates-0.1.2.dist-info/RECORD
