Metadata-Version: 2.1
Name: selia-templates
Version: 0.1.2
Summary: Base templates and css for SELIA
Home-page: https://github.com/CONABIO-audio/selia-templates
Author: CONABIO, Gustavo Everardo Robredo Esquivelzeta, Santiago Martínez Balvanera
Author-email: erobredo@conabio.gob.mx, smartinez@conabio.gob.mx
License: BSD License
Platform: UNKNOWN
Classifier: Environment :: Web Environment
Classifier: Framework :: Django
Classifier: Framework :: Django :: 2.1
Classifier: Intended Audience :: Developers
Classifier: License :: OSI Approved :: BSD License
Classifier: Operating System :: OS Independent
Classifier: Programming Language :: Python
Classifier: Programming Language :: Python :: 3.5
Classifier: Programming Language :: Python :: 3.6
Classifier: Topic :: Internet :: WWW/HTTP
Classifier: Topic :: Internet :: WWW/HTTP :: Dynamic Content
Requires-Dist: django
Requires-Dist: pycountry
Requires-Dist: django-crispy-forms
Requires-Dist: django-widget-tweaks
Requires-Dist: django-autocomplete-light
